rpa_amazon_buyer/__init__.py
rpa_amazon_buyer/api/ProductApi.py
rpa_amazon_buyer/api/__init__.py
rpa_amazon_buyer/command/__init__.py
rpa_amazon_buyer/command/bill/__init__.py
rpa_amazon_buyer/command/bill/service/__init__.py
rpa_amazon_buyer/command/product/__init__.py
rpa_amazon_buyer/command/product/service/ProductService.py
rpa_amazon_buyer/command/product/service/__init__.py
rpa_amazon_buyer/request/__init__.py
rpa_amazon_buyer/service/__init__.py
rpa_amazon_buyer-1.0.2.dist-info/LICENSE
rpa_amazon_buyer-1.0.2.dist-info/METADATA
rpa_amazon_buyer-1.0.2.dist-info/WHEEL
rpa_amazon_buyer-1.0.2.dist-info/top_level.txt
rpa_amazon_buyer-1.0.2.dist-info/RECORD
